{"Statistics": 
    {"BA in Statistics": [[["MATH 13100", "MATH 13200"], ["MATH 15100", "MATH 15200"], ["MATH 16100", "MATH 16200"], ["MATH 16110", "MATH 16210"]], ["MATH 13300", "MATH 15300", "MATH 16300", "MATH 16310", "MATH 18300"], [["MATH 18400", "MATH 18500"], ["MATH 18400", "STAT 28200"], ["MATH 20000", "MATH 20100"], ["STAT 28200", "MATH 20000"], ["MATH 20400", "MATH 20500"], ["MATH 20410", "MATH 20510"], ["MATH 20800", "MATH 20900"]], ["STAT 24300", "MATH 20250", "MATH 20700"], [["STAT 24400", "STAT 24500"], ["STAT 24410", "STAT 24510"]], ["STAT 25100", "STAT 25150", "MATH 23500"], ["STAT 22400", "STAT 22401", "STAT 34300"], [["CMSC 12100", "CMSC 12200"], ["CMSC 15100", "CMSC 15200"], ["CMSC 16100", "CMSC 16200"]], "!ELEC", "!ELEC", "!ELEC", "!ELEC"], 
    "BS in Statistics": [[["MATH 13100", "MATH 13200"], ["MATH 15100", "MATH 15200"], ["MATH 16100", "MATH 16200"], ["MATH 16110", "MATH 16210"]], ["MATH 13300", "MATH 15300", "MATH 16300", "MATH 16310", "MATH 18300"], ["MATH 18400", "MATH 20000", "MATH 20500", "MATH 20510", "MATH 20900"], ["MATH 18500", "MATH 20100", "MATH 27300", "STAT 28200"], ["STAT 24300", "MATH 20250", "MATH 20700"], ["STAT 28000", "MATH 21100"], [["STAT 24400", "STAT 24500"], ["STAT 24410", "STAT 24510"]], ["STAT 25100", "STAT 25150", "MATH 23500"], ["STAT 22400", "STAT 22401", "STAT 34300"], [["CMSC 12100", "CMSC 12200"], ["CMSC 15100", "CMSC 15200"], ["CMSC 16100", "CMSC 16200"]], "!ELEC", "!ELEC", "!ELEC", "!ELEC", "!ELEC", "!ELEC", "!ELEC"]}, 

"Economics":
    {"BA in Economics, Track A": [[["MATH 13100", "MATH 13200"], ["MATH 15100", "MATH 15200"], ["MATH 16100", "MATH 16200"], ["MATH 16110", "MATH 16210"]], ["MATH 13300", "MATH 15300", "MATH 16300", "MATH 16310"], [["ECON 20000", "ECON 20100", "ECON 20200"], ["ECON 20010", "ECON 20110", "ECON 20210"]], ["MATH 19520", "MATH 20400", "MATH 20410", "MATH 20800"], ["MATH 19620", "MATH 20250", "STAT 24300", "MATH 20700"], ["STAT 23400", "STAT 24400", "STAT 24410"], ["ECON 21020", "ECON 21030"], ["ECON 23950", "ECON 23200", "ECMA 33220", "ECON 23330", "ECMA 33330"], "!ELEC", "!ELEC", "!ELEC", "!ELEC"],
    "BA in Economics, Track B": [[["MATH 13100", "MATH 13200"], ["MATH 15100", "MATH 15200"], ["MATH 16100", "MATH 16200"], ["MATH 16110", "MATH 16210"]], ["MATH 13300", "MATH 15300", "MATH 16300", "MATH 16310"], [["ECON 20000", "ECON 20100", "ECON 20200"], ["ECON 20010", "ECON 20110", "ECON 20210"]], ["MATH 19520", "MATH 20400", "MATH 20410", "MATH 20800"], ["ECON 21010"], ["ECON 21020"], ["ECON 23950", "ECON 23200", "ECMA 33220", "ECON 23330", "ECMA 33330"], "!ELEC", "!ELEC", "!ELEC", "!ELEC", "!ELEC"],
    "BA in Economics with Specialization in Business Economics": [[["MATH 13100", "MATH 13200"], ["MATH 15100", "MATH 15200"], ["MATH 16100", "MATH 16200"], ["MATH 16110", "MATH 16210"]], ["ECON 10000", "ECON 20000", "ECON 20010"], ["ECON 10200", "ECON 20200", "ECON 20210"], ["BUSN 20100", "BUSN 20330", "BUSN 20410", "BUSN 20702", "BUSN 20600", "BUSN 20500", "BUSN 20800", "BUSN 20900"], ["ECON 11700", "ECON 20100", "ECON 20700", "ECON 21800"], ["ECON 13000", "ECON 23000", "ECON 16020", "ECON 17100", "ECON 27000", "ECON 23950"], ["ECON 21010", "STAT 22000", "STAT 23400", "STAT 24400", "STAT 24410"], ["ECON 11020", "ECON 21020", "ECON 21030"], "!ELEC", "!ELEC", "!ELEC", "!ELEC", "!ELEC", "!ELEC"],
    "BA in Economics with Specialization in Data Science": [[["MATH 13100", "MATH 13200"], ["MATH 15100", "MATH 15200"], ["MATH 16100", "MATH 16200"], ["MATH 16110", "MATH 16210"]], ["MATH 13300", "MATH 15300", "MATH 16300", "MATH 16310"], ["MATH 19520", "MATH 20400", "MATH 20410", "MATH 20800"], [["ECON 20000", "ECON 20100", "ECON 20200"], ["ECON 20010", "ECON 20110", "ECON 20210"]], ["MATH 19620", "STAT 24300", "MATH 20250", "MATH 20700"], ["STAT 23400", "STAT 24400", "STAT 24410"], ["ECON 21020", "ECON 21030"], ["CMSC 12300", "CMSC 15200", "CMSC 16200"], ["ECON 21300", "ECMA 31340"], ["ECON 21110", "ECMA 31130", "ECON 21150", "ECON 21200", "STAT 26100", "BUSN 20820", "BUSN 41203", "ECON 21410", "ECON 23040", "STAT 27400", "STAT 27725"], ["ECON 21110", "ECMA 31130", "ECON 21150", "ECON 21200", "STAT 26100", "BUSN 20820", "BUSN 41203", "ECON 21410", "ECON 23040", "STAT 27400", "STAT 27725"]]},

"Mathematics":
    {"Mathematics BA": [[["CHEM 10100", "CHEM 10200"], ["CHEM 11100", "CHEM 11200"], ["PHYS 12100", "PHYS 12200"]], [["MATH 13100", "MATH 13200"], ["MATH 15100", "MATH 15200"], ["MATH 16100", "MATH 16200"], ["MATH 16110", "MATH 16210"]], ["CHEM 11300", "PHYS 12300"], ["MATH 16300", "MATH 16310", "MATH 15910"], ["MATH 20250"], [["MATH 20300", "MATH 20400", "MATH 20500"], ["MATH 20310", "MATH 20410", "MATH 20510"], ["MATH 20320", "MATH 20420", "MATH 20520"], ["MATH 20700", "MATH 20800", "MATH 20900"]], "!ELEC", "!ELEC", "!ELEC", "!ELEC", "!ELEC", "!ELEC", ["MATH 25400", "MATH 25700"], ["MATH 25500", "MATH 25800"]],
    "Mathematics BS": [[["CHEM 10100", "CHEM 10200"], ["CHEM 11100", "CHEM 11200"], ["PHYS 12100", "PHYS 12200"]], [["MATH 13100", "MATH 13200"], ["MATH 15100", "MATH 15200"], ["MATH 16100", "MATH 16200"], ["MATH 16110", "MATH 16210"]], ["CHEM 11300", "PHYS 12300"], ["MATH 16300", "MATH 16310", "MATH 15910"], ["MATH 20250"], [["MATH 20300", "MATH 20400", "MATH 20500"], ["MATH 20310", "MATH 20410", "MATH 20510"], ["MATH 20320", "MATH 20420", "MATH 20520"], ["MATH 20700", "MATH 20800", "MATH 20900"]], "!ELEC", "!ELEC", "!ELEC", "!ELEC", "!ELEC", "!ELEC", [["MATH 25400", "MATH 25500"], ["MATH 25700", "MATH 25800"]], "!ELEC", "!ELEC", "!ELEC"],
    "BS in Applied Mathematics": [[["CHEM 10100", "CHEM 10200"], ["CHEM 11100", "CHEM 11200"], ["PHYS 12100", "PHYS 12200"]], [["MATH 13100", "MATH 13200"], ["MATH 15100", "MATH 15200"], ["MATH 16100", "MATH 16200"], ["MATH 16110", "MATH 16210"]], ["CHEM 11300", "PHYS 12300"], ["MATH 16300", "MATH 16310", "MATH 15910"], ["MATH 20250"], [["MATH 20300", "MATH 20400", "MATH 20500"], ["MATH 20310", "MATH 20410", "MATH 20510"], ["MATH 20320", "MATH 20420", "MATH 20520"], ["MATH 20700", "MATH 20800", "MATH 20900"]], ["MATH 21100", "MATH 21200"], ["MATH 25400", "MATH 25700"], "MATH 27000", "MATH 27300", "MATH 27500", "!ELEC", "!ELEC", "!ELEC", "!ELEC", "!ELEC", "!ELEC"],
    "BS in Mathematics with Specialization in Economics": [[["CHEM 10100", "CHEM 10200"], ["CHEM 11100", "CHEM 11200"], ["PHYS 12100", "PHYS 12200"]], [["MATH 13100", "MATH 13200"], ["MATH 15100", "MATH 15200"], ["MATH 16100", "MATH 16200"], ["MATH 16110", "MATH 16210"]], ["CHEM 11300", "PHYS 12300"], ["MATH 16300", "MATH 16310", "MATH 15910"], ["MATH 20250"], [["MATH 20300", "MATH 20400", "MATH 20500"], ["MATH 20310", "MATH 20410", "MATH 20510"], ["MATH 20320", "MATH 20420", "MATH 20520"], ["MATH 20700", "MATH 20800", "MATH 20900"]], ["MATH 25400", "MATH 25700"], ["MATH 27000", "MATH 27100", "MATH 27200", "MATH 27300", "MATH 23500", "MATH 26200"], ["MATH 27000", "MATH 27100", "MATH 27200", "MATH 27300", "MATH 23500", "MATH 26200"], ["STAT 25100", "STAT 25150"], ["STAT 23400", "STAT 24400", "STAT 24410"], [["ECON 20000", "ECON 20100", "ECON 20200"], ["ECON 20010", "ECON 20110", "ECON 20210"]], ["ECON 21020", "ECON 21030"], "!ELEC", "!ELEC", "!ELEC"]},

"Physics":
    {"BA in Physics": [[["PHYS 13100", "PHYS 13200"], ["PHYS 14100", "PHYS 14200"]], [["MATH 15100", "MATH 15200"], ["MATH 16100", "MATH 16200"]], ["PHYS 13300", "PHYS 14300"], [["MATH 18300", "MATH 18400", "MATH 18500", "MATH 18600"], ["MATH 20300", "MATH 20400", "MATH 20500", "MATH 20250"], ["MATH 20700", "MATH 20800", "MATH 20900", "MATH 16300"]], ["PHYS 18500"], [["PHYS 21101", "PHYS 21102", "PHYS 21103"]], [["PHYS 22500", "PHYS 22700"]], [["PHYS 23410", "PHYS 23510", "PHYS 24310"]], ["PHYS 27900"], "!ELEC", "!ELEC", "!ELEC"]},
    
"Chemistry":
    {"BA in Chemistry": [[["CHEM 11100", "CHEM 11200"]], [["MATH 15100", "MATH 15200"], ["MATH 16100", "MATH 16200"], ["MATH 13100", "MATH 13200"]], ["CHEM 11300", "CHEM 12300"], ["MATH 18300", "STAT 24300", "MATH 19620", "MATH 20250"], [["MATH 18400", "MATH 18500"]], [["PHYS 13100", "PHYS 13200", "PHYS 13300"]], ["CHEM 20100"], [["CHEM 22000", "CHEM 22100", "CHEM 22200"], ["CHEM 23000", "CHEM 23100", "CHEM 23200"]], [["CHEM 26100", "CHEM 26200"]], ["CHEM 26700"]],
    "BS in Chemistry": [[["CHEM 11100", "CHEM 11200"]], [["MATH 15100", "MATH 15200"], ["MATH 16100", "MATH 16200"], ["MATH 13100", "MATH 13200"]], ["CHEM 11300", "CHEM 12300"], [["MATH 18300", "MATH 18400", "MATH 18500"]], [["CHEM 20100", "CHEM 20200"]], [["PHYS 13100", "PHYS 13200", "PHYS 13300"]], [["CHEM 22000", "CHEM 22100", "CHEM 22200"]], ["CHEM 23300"], [["CHEM 26100", "CHEM 26200", "CHEM 26300"]], ["CHEM 26700"], ["CHEM 22700", "CHEM 26800"]]}}